<annotation>
	<folder>n03790512</folder>
	<filename>n03790512_2489</filename>
	<source>
		<database>ILSVRC_2013</database>
	</source>
	<size>
		<width>500</width>
		<height>268</height>
	</size>
	<object>
		<name>n03790512</name>
		<bndbox>
			<xmin>184</xmin>
			<xmax>253</xmax>
			<ymin>41</ymin>
			<ymax>98</ymax>
		</bndbox>
	</object>
	<object>
		<name>n03790512</name>
		<bndbox>
			<xmin>222</xmin>
			<xmax>359</xmax>
			<ymin>69</ymin>
			<ymax>158</ymax>
		</bndbox>
	</object>
	<object>
		<name>n03790512</name>
		<bndbox>
			<xmin>351</xmin>
			<xmax>435</xmax>
			<ymin>55</ymin>
			<ymax>151</ymax>
		</bndbox>
	</object>
	<object>
		<name>n03790512</name>
		<bndbox>
			<xmin>16</xmin>
			<xmax>283</xmax>
			<ymin>98</ymin>
			<ymax>263</ymax>
		</bndbox>
	</object>
</annotation>
