<annotation>
	<folder>n03769881</folder>
	<filename>n03769881_13066</filename>
	<source>
		<database>ILSVRC_2013</database>
	</source>
	<size>
		<width>500</width>
		<height>375</height>
	</size>
	<object>
		<name>n02924116</name>
		<subcategory>n03769881</subcategory>
		<bndbox>
			<xmin>183</xmin>
			<xmax>469</xmax>
			<ymin>72</ymin>
			<ymax>301</ymax>
		</bndbox>
	</object>
	<object>
		<name>n02924116</name>
		<subcategory>n03769881</subcategory>
		<bndbox>
			<xmin>76</xmin>
			<xmax>232</xmax>
			<ymin>72</ymin>
			<ymax>232</ymax>
		</bndbox>
	</object>
</annotation>
