<annotation>
	<folder>n04487081</folder>
	<filename>n04487081_33251</filename>
	<source>
		<database>ILSVRC_2013</database>
	</source>
	<size>
		<width>500</width>
		<height>332</height>
	</size>
	<object>
		<name>n02924116</name>
		<subcategory>n04487081</subcategory>
		<bndbox>
			<xmin>346</xmin>
			<xmax>406</xmax>
			<ymin>169</ymin>
			<ymax>248</ymax>
		</bndbox>
	</object>
	<object>
		<name>n02924116</name>
		<subcategory>n04487081</subcategory>
		<bndbox>
			<xmin>180</xmin>
			<xmax>355</xmax>
			<ymin>49</ymin>
			<ymax>270</ymax>
		</bndbox>
	</object>
	<object>
		<name>n00007846</name>
		<bndbox>
			<xmin>423</xmin>
			<xmax>443</xmax>
			<ymin>198</ymin>
			<ymax>249</ymax>
		</bndbox>
	</object>
</annotation>
